django_entries/__init__.py
django_entries/admin.py
django_entries/apps.py
django_entries/docs/active_search.md
django_entries/docs/infinity_scroll.md
django_entries/forms.py
django_entries/migrations/0001_initial.py
django_entries/migrations/__init__.py
django_entries/models.py
django_entries/static/css/starter.css
django_entries/static/img/favicons/android-chrome-192x192.png
django_entries/static/img/favicons/android-chrome-512x512.png
django_entries/static/img/favicons/apple-touch-icon.png
django_entries/static/img/favicons/favicon-16x16.png
django_entries/static/img/favicons/favicon-32x32.png
django_entries/static/img/favicons/favicon.ico
django_entries/static/img/favicons/site.webmanifest
django_entries/templates/about.html
django_entries/templates/base.html
django_entries/templates/base_template/_messages.html
django_entries/templates/base_template/_nav.html
django_entries/templates/entries/entry_detail.html
django_entries/templates/entries/entry_edit.html
django_entries/templates/entries/entry_item.html
django_entries/templates/entries/entry_list.html
django_entries/templates/entries/entry_next.html
django_entries/templates/home.html
django_entries/urls.py
django_entries/utils.py
django_entries/validators.py
django_entries/views.py
django_entries-0.1.12.dist-info/LICENSE
django_entries-0.1.12.dist-info/METADATA
django_entries-0.1.12.dist-info/WHEEL
django_entries-0.1.12.dist-info/RECORD
