Metadata-Version: 2.1
Name: django-entries
Version: 0.1.12
Summary: Entries is a helper Django app, CRUD.
Home-page: https://github.com/justmars/django-entries
Author: Marcelino G. Veloso III
Author-email: mars@veloso.one
Requires-Python: >=3.11,<4.0
Classifier: Programming Language :: Python :: 3
Classifier: Programming Language :: Python :: 3.11
Requires-Dist: Django (>=4.2,<5.0)
Requires-Dist: Markdown (>=3.3.6,<4.0.0)
Requires-Dist: bleach (>=4.1.0,<5.0.0)
Requires-Dist: django-extensions (>=3.2,<4.0)
Requires-Dist: markdownify (>=0.10,<0.11)
Project-URL: Repository, https://github.com/justmars/django-entries
